spellbind/__init__.py
spellbind/actions.py
spellbind/bool_values.py
spellbind/deriveds.py
spellbind/emitters.py
spellbind/event.py
spellbind/float_values.py
spellbind/functions.py
spellbind/int_collections.py
spellbind/int_values.py
spellbind/numbers.py
spellbind/observable_collections.py
spellbind/observable_sequences.py
spellbind/observables.py
spellbind/py.typed
spellbind/str_collections.py
spellbind/str_values.py
spellbind/values.py
spellbind-0.4.1.dist-info/licenses/LICENSE
spellbind-0.4.1.dist-info/METADATA
spellbind-0.4.1.dist-info/WHEEL
spellbind-0.4.1.dist-info/top_level.txt
spellbind-0.4.1.dist-info/RECORD
