Metadata-Version: 2.4
Name: spellbind
Version: 0.4.1
Summary: A library which provides observable values to which other values can be bound
Author-email: Georg Plaz <georg.plaz@gmail.com>
License: MIT License
Project-URL: Homepage, https://github.com/FancyNeuron/spellbind
Project-URL: Repository, https://github.com/FancyNeuron/spellbind
Project-URL: Issues, https://github.com/FancyNeuron/spellbind/issues
Project-URL: Documentation, https://github.com/FancyNeuron/spellbind#readme
Keywords: reactive,programming,computed,derived,values,variables,data-binding,observable,events,event-driven
Classifier: Development Status :: 4 - Beta
Classifier: Intended Audience :: Developers
Classifier: License :: OSI Approved :: MIT License
Classifier: Operating System :: OS Independent
Classifier: Programming Language :: Python :: 3
Classifier: Programming Language :: Python :: 3.10
Classifier: Programming Language :: Python :: 3.12
Classifier: Topic :: Software Development :: Libraries
Classifier: Topic :: Software Development :: Libraries :: Python Modules
Classifier: Typing :: Typed
Requires-Python: >=3.10
License-File: LICENSE
Requires-Dist: typing_extensions<5,>=4.13
Provides-Extra: testing
Requires-Dist: pytest; extra == "testing"
Requires-Dist: pytest-cov; extra == "testing"
Requires-Dist: flake8; extra == "testing"
Requires-Dist: mypy; extra == "testing"
Requires-Dist: setuptools_scm; extra == "testing"
Dynamic: license-file
